{
  "book": "1CO",
  "chapter": 7,
  "url": "https://www.debijbel.nl/bijbel/HSV/1CO.7",
  "verses": [
    {
      "verse": 1,
      "text": "Wat nu de dingen betreft waarover u mij geschreven hebt: het is goed voor een mens om geen vrouw aan te raken."
    },
    {
      "verse": 2,
      "text": "Maar laat vanwege"
    },
    {
      "verse": 2,
      "text": "allerlei"
    },
    {
      "verse": 2,
      "text": "vormen van hoererij iedere"
    },
    {
      "verse": 2,
      "text": "man"
    },
    {
      "verse": 2,
      "text": "zijn eigen vrouw hebben en iedere"
    },
    {
      "verse": 2,
      "text": "vrouw"
    },
    {
      "verse": 2,
      "text": "haar eigen man."
    },
    {
      "verse": 3,
      "text": "Laat de man aan"
    },
    {
      "verse": 3,
      "text": "zijn"
    },
    {
      "verse": 3,
      "text": "vrouw de verschuldigde bereidwilligheid betonen en evenzo ook de vrouw aan"
    },
    {
      "verse": 3,
      "text": "haar"
    },
    {
      "verse": 3,
      "text": "man."
    },
    {
      "verse": 4,
      "text": "De vrouw heeft niet de beschikking over haar eigen lichaam, maar de man. En evenzo heeft ook de man niet de beschikking over zijn eigen lichaam, maar de vrouw."
    },
    {
      "verse": 5,
      "text": "Onttrek u niet aan elkaar, behalve dan met"
    },
    {
      "verse": 5,
      "text": "onderling"
    },
    {
      "verse": 5,
      "text": "goedvinden voor een"
    },
    {
      "verse": 5,
      "text": "bepaalde"
    },
    {
      "verse": 5,
      "text": "tijd, om u te wijden aan vasten en bidden. Kom daarna weer bij elkaar, opdat de satan u niet zal verzoeken omdat u zich niet kunt onthouden."
    },
    {
      "verse": 6,
      "text": "Dit zeg ik echter als tegemoetkoming, niet als bevel."
    },
    {
      "verse": 7,
      "text": "Want ik zou wel willen dat alle mensen waren zoals ikzelf,"
    },
    {
      "verse": 7,
      "text": "maar ieder heeft zijn eigen genadegave van God, de één op deze wijze, de ander op die wijze."
    },
    {
      "verse": 8,
      "text": "Maar ik zeg tegen de ongehuwden en de weduwen: Het is goed voor hen, als zij blijven zoals ik."
    },
    {
      "verse": 9,
      "text": "Maar als zij zich niet kunnen beheersen, laten zij dan trouwen, want het is beter te trouwen dan"
    },
    {
      "verse": 9,
      "text": "van begeerte"
    },
    {
      "verse": 9,
      "text": "te branden."
    },
    {
      "verse": 10,
      "text": "Maar de gehuwden beveel ik – niet ik, maar de Heere –"
    },
    {
      "verse": 10,
      "text": "dat een vrouw niet zal scheiden van"
    },
    {
      "verse": 10,
      "text": "haar"
    },
    {
      "verse": 10,
      "text": "man"
    },
    {
      "verse": 11,
      "text": "– en als zij toch gaat scheiden, moet zij ongehuwd blijven of zich met"
    },
    {
      "verse": 11,
      "text": "haar"
    },
    {
      "verse": 11,
      "text": "man verzoenen – en dat een man zijn vrouw niet zal verlaten."
    },
    {
      "verse": 12,
      "text": "Maar tegen de anderen zeg ík, niet de Heere: Als een broeder een ongelovige vrouw heeft en zij er van harte mee instemt bij hem te wonen, moet hij haar niet verlaten."
    },
    {
      "verse": 13,
      "text": "En als een vrouw een ongelovige man heeft en deze stemt er van harte mee in bij haar te wonen, moet zij hem niet verlaten."
    },
    {
      "verse": 14,
      "text": "Want de ongelovige man is geheiligd door"
    },
    {
      "verse": 14,
      "text": "zijn"
    },
    {
      "verse": 14,
      "text": "vrouw en de ongelovige vrouw is geheiligd door"
    },
    {
      "verse": 14,
      "text": "haar"
    },
    {
      "verse": 14,
      "text": "man. Anders waren immers uw kinderen onrein, maar nu zijn zij heilig."
    },
    {
      "verse": 15,
      "text": "Maar als de ongelovige scheiden wil, laat hij scheiden. De broeder of de zuster is in zulke gevallen niet gebonden. God heeft ons echter tot vrede geroepen."
    },
    {
      "verse": 16,
      "text": "Want hoe weet u, vrouw, of u"
    },
    {
      "verse": 16,
      "text": "uw"
    },
    {
      "verse": 16,
      "text": "man zult behouden? Of hoe weet u, man, of u"
    },
    {
      "verse": 16,
      "text": "uw"
    },
    {
      "verse": 16,
      "text": "vrouw zult behouden?"
    },
    {
      "verse": 17,
      "text": "Maar zoals God aan ieder heeft toebedeeld, zoals de Heere ieder geroepen heeft, zó moet hij wandelen. En zo schrijf ik"
    },
    {
      "verse": 17,
      "text": "het"
    },
    {
      "verse": 17,
      "text": "in alle gemeenten voor."
    },
    {
      "verse": 18,
      "text": "Is iemand als besnedene geroepen, dan moet hij"
    },
    {
      "verse": 18,
      "text": "die besnijdenis"
    },
    {
      "verse": 18,
      "text": "niet ongedaan laten maken. Is iemand geroepen die onbesneden is,"
    },
    {
      "verse": 18,
      "text": "dan moet hij zich niet laten besnijden."
    },
    {
      "verse": 19,
      "text": "Besneden zijn is niets en onbesneden zijn is niets, maar het in acht nemen van de geboden van God."
    },
    {
      "verse": 20,
      "text": "Laat ieder blijven in de roeping waarin hij geroepen is."
    },
    {
      "verse": 21,
      "text": "Bent u als slaaf geroepen, dan moet u zich"
    },
    {
      "verse": 21,
      "text": "daarover"
    },
    {
      "verse": 21,
      "text": "niet bekommeren. Kunt u echter ook vrij worden, maak dan liever"
    },
    {
      "verse": 21,
      "text": "van die gelegenheid"
    },
    {
      "verse": 21,
      "text": "gebruik."
    },
    {
      "verse": 22,
      "text": "Wie namelijk als slaaf geroepen is in de Heere, is een vrijgelatene van de Heere. Evenzo is hij die als vrije geroepen is, een slaaf van Christus."
    },
    {
      "verse": 23,
      "text": "U bent duur gekocht; word"
    },
    {
      "verse": 23,
      "text": "dus"
    },
    {
      "verse": 23,
      "text": "geen slaven van mensen."
    },
    {
      "verse": 24,
      "text": "Laat ieder voor"
    },
    {
      "verse": 24,
      "text": "het aangezicht van"
    },
    {
      "verse": 24,
      "text": "God blijven, broeders, in de"
    },
    {
      "verse": 24,
      "text": "staat"
    },
    {
      "verse": 24,
      "text": "waarin hij geroepen is."
    },
    {
      "verse": 25,
      "text": "Wat betreft hen die"
    },
    {
      "verse": 25,
      "text": "nog"
    },
    {
      "verse": 25,
      "text": "maagd zijn, heb ik geen bevel van de Heere. Ik geef echter mijn mening als iemand die barmhartigheid van de Heere heeft gekregen om trouw te zijn."
    },
    {
      "verse": 26,
      "text": "Ik denk dat dit goed is met het oog op de aanstaande nood,"
    },
    {
      "verse": 26,
      "text": "namelijk dat het voor een mens goed is om zo te zijn."
    },
    {
      "verse": 27,
      "text": "Bent u aan een vrouw verbonden, zoek geen losmaking. Bent u vrij van een vrouw, zoek"
    },
    {
      "verse": 27,
      "text": "dan"
    },
    {
      "verse": 27,
      "text": "geen vrouw."
    },
    {
      "verse": 28,
      "text": "Maar ook als u trouwt, zondigt u niet. Ook als een meisje dat nog maagd is, trouwt, zondigt zij niet. Zulke mensen echter zullen wel verdrukking hebben in het vlees en dat"
    },
    {
      "verse": 28,
      "text": "wil"
    },
    {
      "verse": 28,
      "text": "ik u besparen."
    },
    {
      "verse": 29,
      "text": "Maar dit zeg ik, broeders, dat de tijd beperkt is. Laten zij die vrouwen hebben, voortaan zijn alsof ze die niet hebben,"
    },
    {
      "verse": 30,
      "text": "en zij die huilen, alsof zij niet huilen, en zij die blij zijn, alsof zij niet blij zijn, en zij die kopen, alsof zij niet bezitten,"
    },
    {
      "verse": 31,
      "text": "en zij die van deze wereld gebruikmaken, alsof zij die niet gebruiken."
    },
    {
      "verse": 31,
      "text": "Immers, de gedaante van deze wereld gaat voorbij."
    },
    {
      "verse": 32,
      "text": "En ik wil dat u zonder zorgen bent."
    },
    {
      "verse": 32,
      "text": "De ongehuwde draagt zorg voor de dingen van de Heere, hoe hij de Heere zal behagen."
    },
    {
      "verse": 33,
      "text": "Wie echter gehuwd is, draagt zorg voor de dingen van de wereld, hoe hij"
    },
    {
      "verse": 33,
      "text": "zijn"
    },
    {
      "verse": 33,
      "text": "vrouw zal behagen."
    },
    {
      "verse": 34,
      "text": "Er is onderscheid tussen de"
    },
    {
      "verse": 34,
      "text": "gehuwde"
    },
    {
      "verse": 34,
      "text": "vrouw en het meisje dat nog maagd is. De ongehuwde draagt zorg voor de dingen van de Heere om zowel naar lichaam als naar geest heilig te zijn. Zij echter die gehuwd is, draagt zorg voor de dingen van de wereld, hoe zij"
    },
    {
      "verse": 34,
      "text": "haar"
    },
    {
      "verse": 34,
      "text": "man zal behagen."
    },
    {
      "verse": 35,
      "text": "En dit zeg ik tot uw eigen voordeel, niet om een strik over u heen te werpen, maar"
    },
    {
      "verse": 35,
      "text": "om u te leiden"
    },
    {
      "verse": 35,
      "text": "tot eerbaar"
    },
    {
      "verse": 35,
      "text": "gedrag"
    },
    {
      "verse": 35,
      "text": "en blijvende toewijding aan de Heere, zonder afgeleid te worden."
    },
    {
      "verse": 36,
      "text": "Maar als iemand denkt dat hij ongepast handelt ten opzichte van zijn"
    },
    {
      "verse": 36,
      "text": "aanstaande vrouw"
    },
    {
      "verse": 36,
      "text": "die nog maagd"
    },
    {
      "verse": 36,
      "text": "is"
    },
    {
      "verse": 36,
      "text": ", als de jaren van haar jeugd voorbij zijn en het op deze wijze behoort te gebeuren, laat hij doen wat hij wil, hij zondigt niet: laten zij trouwen."
    },
    {
      "verse": 37,
      "text": "Maar wie in zijn hart vastbesloten is en"
    },
    {
      "verse": 37,
      "text": "er"
    },
    {
      "verse": 37,
      "text": "niet"
    },
    {
      "verse": 37,
      "text": "toe"
    },
    {
      "verse": 37,
      "text": "genoodzaakt wordt, maar macht heeft over zijn eigen wil en in zijn hart besloten heeft dat hij zijn eigen"
    },
    {
      "verse": 37,
      "text": "aanstaande vrouw"
    },
    {
      "verse": 37,
      "text": "die nog maagd"
    },
    {
      "verse": 37,
      "text": "is"
    },
    {
      "verse": 37,
      "text": ","
    },
    {
      "verse": 37,
      "text": "zo"
    },
    {
      "verse": 37,
      "text": "zal houden, die handelt"
    },
    {
      "verse": 37,
      "text": "ook"
    },
    {
      "verse": 37,
      "text": "goed."
    },
    {
      "verse": 38,
      "text": "Dus: ook wie ten huwelijk geeft, handelt goed, maar wie niet ten huwelijk geeft, handelt beter."
    },
    {
      "verse": 39,
      "text": "Een vrouw is door de wet gebonden, zolang haar man leeft. Als haar man echter ontslapen is, is zij vrij om te trouwen met wie zij wil,"
    },
    {
      "verse": 39,
      "text": "maar"
    },
    {
      "verse": 39,
      "text": "alleen in de Heere."
    },
    {
      "verse": 40,
      "text": "Maar zij is gelukkiger, als zij zo blijft, naar mijn mening. En ik denk ook dat ik"
    },
    {
      "verse": 40,
      "text": "de Geest van God heb."
    }
  ],
  "full_text": "1 Wat nu de dingen betreft waarover u mij geschreven hebt: het is goed voor een mens om geen vrouw aan te raken.\n2 Maar laat vanwege\n2 allerlei\n2 vormen van hoererij iedere\n2 man\n2 zijn eigen vrouw hebben en iedere\n2 vrouw\n2 haar eigen man.\n3 Laat de man aan\n3 zijn\n3 vrouw de verschuldigde bereidwilligheid betonen en evenzo ook de vrouw aan\n3 haar\n3 man.\n4 De vrouw heeft niet de beschikking over haar eigen lichaam, maar de man. En evenzo heeft ook de man niet de beschikking over zijn eigen lichaam, maar de vrouw.\n5 Onttrek u niet aan elkaar, behalve dan met\n5 onderling\n5 goedvinden voor een\n5 bepaalde\n5 tijd, om u te wijden aan vasten en bidden. Kom daarna weer bij elkaar, opdat de satan u niet zal verzoeken omdat u zich niet kunt onthouden.\n6 Dit zeg ik echter als tegemoetkoming, niet als bevel.\n7 Want ik zou wel willen dat alle mensen waren zoals ikzelf,\n7 maar ieder heeft zijn eigen genadegave van God, de één op deze wijze, de ander op die wijze.\n8 Maar ik zeg tegen de ongehuwden en de weduwen: Het is goed voor hen, als zij blijven zoals ik.\n9 Maar als zij zich niet kunnen beheersen, laten zij dan trouwen, want het is beter te trouwen dan\n9 van begeerte\n9 te branden.\n10 Maar de gehuwden beveel ik – niet ik, maar de Heere –\n10 dat een vrouw niet zal scheiden van\n10 haar\n10 man\n11 – en als zij toch gaat scheiden, moet zij ongehuwd blijven of zich met\n11 haar\n11 man verzoenen – en dat een man zijn vrouw niet zal verlaten.\n12 Maar tegen de anderen zeg ík, niet de Heere: Als een broeder een ongelovige vrouw heeft en zij er van harte mee instemt bij hem te wonen, moet hij haar niet verlaten.\n13 En als een vrouw een ongelovige man heeft en deze stemt er van harte mee in bij haar te wonen, moet zij hem niet verlaten.\n14 Want de ongelovige man is geheiligd door\n14 zijn\n14 vrouw en de ongelovige vrouw is geheiligd door\n14 haar\n14 man. Anders waren immers uw kinderen onrein, maar nu zijn zij heilig.\n15 Maar als de ongelovige scheiden wil, laat hij scheiden. De broeder of de zuster is in zulke gevallen niet gebonden. God heeft ons echter tot vrede geroepen.\n16 Want hoe weet u, vrouw, of u\n16 uw\n16 man zult behouden? Of hoe weet u, man, of u\n16 uw\n16 vrouw zult behouden?\n17 Maar zoals God aan ieder heeft toebedeeld, zoals de Heere ieder geroepen heeft, zó moet hij wandelen. En zo schrijf ik\n17 het\n17 in alle gemeenten voor.\n18 Is iemand als besnedene geroepen, dan moet hij\n18 die besnijdenis\n18 niet ongedaan laten maken. Is iemand geroepen die onbesneden is,\n18 dan moet hij zich niet laten besnijden.\n19 Besneden zijn is niets en onbesneden zijn is niets, maar het in acht nemen van de geboden van God.\n20 Laat ieder blijven in de roeping waarin hij geroepen is.\n21 Bent u als slaaf geroepen, dan moet u zich\n21 daarover\n21 niet bekommeren. Kunt u echter ook vrij worden, maak dan liever\n21 van die gelegenheid\n21 gebruik.\n22 Wie namelijk als slaaf geroepen is in de Heere, is een vrijgelatene van de Heere. Evenzo is hij die als vrije geroepen is, een slaaf van Christus.\n23 U bent duur gekocht; word\n23 dus\n23 geen slaven van mensen.\n24 Laat ieder voor\n24 het aangezicht van\n24 God blijven, broeders, in de\n24 staat\n24 waarin hij geroepen is.\n25 Wat betreft hen die\n25 nog\n25 maagd zijn, heb ik geen bevel van de Heere. Ik geef echter mijn mening als iemand die barmhartigheid van de Heere heeft gekregen om trouw te zijn.\n26 Ik denk dat dit goed is met het oog op de aanstaande nood,\n26 namelijk dat het voor een mens goed is om zo te zijn.\n27 Bent u aan een vrouw verbonden, zoek geen losmaking. Bent u vrij van een vrouw, zoek\n27 dan\n27 geen vrouw.\n28 Maar ook als u trouwt, zondigt u niet. Ook als een meisje dat nog maagd is, trouwt, zondigt zij niet. Zulke mensen echter zullen wel verdrukking hebben in het vlees en dat\n28 wil\n28 ik u besparen.\n29 Maar dit zeg ik, broeders, dat de tijd beperkt is. Laten zij die vrouwen hebben, voortaan zijn alsof ze die niet hebben,\n30 en zij die huilen, alsof zij niet huilen, en zij die blij zijn, alsof zij niet blij zijn, en zij die kopen, alsof zij niet bezitten,\n31 en zij die van deze wereld gebruikmaken, alsof zij die niet gebruiken.\n31 Immers, de gedaante van deze wereld gaat voorbij.\n32 En ik wil dat u zonder zorgen bent.\n32 De ongehuwde draagt zorg voor de dingen van de Heere, hoe hij de Heere zal behagen.\n33 Wie echter gehuwd is, draagt zorg voor de dingen van de wereld, hoe hij\n33 zijn\n33 vrouw zal behagen.\n34 Er is onderscheid tussen de\n34 gehuwde\n34 vrouw en het meisje dat nog maagd is. De ongehuwde draagt zorg voor de dingen van de Heere om zowel naar lichaam als naar geest heilig te zijn. Zij echter die gehuwd is, draagt zorg voor de dingen van de wereld, hoe zij\n34 haar\n34 man zal behagen.\n35 En dit zeg ik tot uw eigen voordeel, niet om een strik over u heen te werpen, maar\n35 om u te leiden\n35 tot eerbaar\n35 gedrag\n35 en blijvende toewijding aan de Heere, zonder afgeleid te worden.\n36 Maar als iemand denkt dat hij ongepast handelt ten opzichte van zijn\n36 aanstaande vrouw\n36 die nog maagd\n36 is\n36 , als de jaren van haar jeugd voorbij zijn en het op deze wijze behoort te gebeuren, laat hij doen wat hij wil, hij zondigt niet: laten zij trouwen.\n37 Maar wie in zijn hart vastbesloten is en\n37 er\n37 niet\n37 toe\n37 genoodzaakt wordt, maar macht heeft over zijn eigen wil en in zijn hart besloten heeft dat hij zijn eigen\n37 aanstaande vrouw\n37 die nog maagd\n37 is\n37 ,\n37 zo\n37 zal houden, die handelt\n37 ook\n37 goed.\n38 Dus: ook wie ten huwelijk geeft, handelt goed, maar wie niet ten huwelijk geeft, handelt beter.\n39 Een vrouw is door de wet gebonden, zolang haar man leeft. Als haar man echter ontslapen is, is zij vrij om te trouwen met wie zij wil,\n39 maar\n39 alleen in de Heere.\n40 Maar zij is gelukkiger, als zij zo blijft, naar mijn mening. En ik denk ook dat ik\n40 de Geest van God heb.",
  "verse_count": 123,
  "translation": "HSV"
}