{
  "book": "2KI",
  "chapter": 7,
  "url": "https://www.debijbel.nl/bijbel/HSV/2KI.7",
  "verses": [
    {
      "verse": 1,
      "text": "Toen zei Elisa: Hoor het woord van de"
    },
    {
      "verse": 1,
      "text": "HEERE"
    },
    {
      "verse": 1,
      "text": ". Zo zegt de"
    },
    {
      "verse": 1,
      "text": "HEERE"
    },
    {
      "verse": 1,
      "text": ": Morgen omstreeks deze tijd zal in de poort van Samaria een maat meelbloem"
    },
    {
      "verse": 1,
      "text": "verkocht worden"
    },
    {
      "verse": 1,
      "text": "voor een"
    },
    {
      "verse": 1,
      "text": "zilveren"
    },
    {
      "verse": 1,
      "text": "sikkel,"
    },
    {
      "verse": 1,
      "text": "en twee maten"
    },
    {
      "verse": 1,
      "text": "gerst voor een sikkel."
    },
    {
      "verse": 2,
      "text": "Maar een officier, op wiens hand de koning leunde, antwoordde de man Gods en zei: Zie, al maakt de"
    },
    {
      "verse": 2,
      "text": "HEERE"
    },
    {
      "verse": 2,
      "text": "sluizen in de hemel – hoe zou dit"
    },
    {
      "verse": 2,
      "text": "kunnen"
    },
    {
      "verse": 2,
      "text": "gebeuren? Maar hij zei: Zie, u zult het met uw ogen zien, maar er niet van eten."
    },
    {
      "verse": 3,
      "text": "Er waren vier melaatse mannen"
    },
    {
      "verse": 3,
      "text": "bij"
    },
    {
      "verse": 3,
      "text": "de ingang van de poort. Zij zeiden tegen elkaar: Waarom blijven wij hier totdat wij sterven?"
    },
    {
      "verse": 4,
      "text": "Als wij zeggen: Wij zullen de stad binnengaan – er is honger in de stad, dan zullen wij daar sterven; en als wij hier blijven, zullen wij"
    },
    {
      "verse": 4,
      "text": "ook"
    },
    {
      "verse": 4,
      "text": "sterven. Nu dan, kom, laten wij naar het legerkamp van de Syriërs overlopen. Als zij ons laten leven,"
    },
    {
      "verse": 4,
      "text": "dan"
    },
    {
      "verse": 4,
      "text": "zullen wij leven, en als zij ons doden, laten we"
    },
    {
      "verse": 4,
      "text": "dan maar"
    },
    {
      "verse": 4,
      "text": "sterven."
    },
    {
      "verse": 5,
      "text": "En in de"
    },
    {
      "verse": 5,
      "text": "avond"
    },
    {
      "verse": 5,
      "text": "schemering stonden zij op om het legerkamp van de Syriërs in te gaan. Toen zij aan de rand van het legerkamp van de Syriërs kwamen, zie, was er niemand."
    },
    {
      "verse": 6,
      "text": "De Heere had het leger van de Syriërs namelijk een"
    },
    {
      "verse": 6,
      "text": "geluid laten horen van strijdwagens en een geluid van paarden – het geluid van een groot leger – zodat zij tegen elkaar zeiden: Zie, de koning van Israël heeft de koningen van de Hethieten en de koningen van de Egyptenaren tegen ons ingehuurd om ons aan te vallen."
    },
    {
      "verse": 7,
      "text": "Zij waren opgesprongen en in de"
    },
    {
      "verse": 7,
      "text": "avond"
    },
    {
      "verse": 7,
      "text": "schemering weggevlucht. Zij hadden hun tenten achtergelaten, hun paarden en hun ezels,"
    },
    {
      "verse": 7,
      "text": "en"
    },
    {
      "verse": 7,
      "text": "het legerkamp zoals het was, en waren gevlucht voor hun leven."
    },
    {
      "verse": 8,
      "text": "Toen nu deze melaatsen aan de rand van het legerkamp kwamen, gingen zij een tent binnen, aten en dronken, namen vandaar zilver, goud en kleren mee, en gingen het verbergen. Daarna keerden zij terug, gingen een andere tent binnen, namen ook daaruit"
    },
    {
      "verse": 8,
      "text": "het een en ander"
    },
    {
      "verse": 8,
      "text": "weg en gingen het"
    },
    {
      "verse": 8,
      "text": "eveneens"
    },
    {
      "verse": 8,
      "text": "verbergen."
    },
    {
      "verse": 9,
      "text": "Toen zeiden zij tegen elkaar: Wij doen"
    },
    {
      "verse": 9,
      "text": "hier"
    },
    {
      "verse": 9,
      "text": "niet goed"
    },
    {
      "verse": 9,
      "text": "aan"
    },
    {
      "verse": 9,
      "text": ". Deze dag is een dag met een goede boodschap en wij zwijgen"
    },
    {
      "verse": 9,
      "text": "erover"
    },
    {
      "verse": 9,
      "text": ". Als wij wachten tot het morgenlicht, staan wij schuldig."
    },
    {
      "verse": 9,
      "text": "Nu dan, kom, laten wij"
    },
    {
      "verse": 9,
      "text": "dit"
    },
    {
      "verse": 9,
      "text": "in het huis van de koning gaan vertellen."
    },
    {
      "verse": 10,
      "text": "Zij kwamen, riepen naar de poortwachter van de stad en vertelden hun: Wij zijn naar het legerkamp van de Syriërs gegaan, en zie, daar was niemand"
    },
    {
      "verse": 10,
      "text": "meer"
    },
    {
      "verse": 10,
      "text": "– geen geluid van mensen, alleen de paarden, vastgebonden; en de ezels, vastgebonden; en de tenten, zoals zij waren."
    },
    {
      "verse": 11,
      "text": "En deze riep de"
    },
    {
      "verse": 11,
      "text": "andere"
    },
    {
      "verse": 11,
      "text": "poortwachters en die vertelden"
    },
    {
      "verse": 11,
      "text": "het"
    },
    {
      "verse": 11,
      "text": "binnen in het huis van de koning."
    },
    {
      "verse": 12,
      "text": "En de koning stond 's nachts op en zei tegen zijn dienaren: Laat mij u toch vertellen wat de Syriërs ons gedaan hebben. Zij weten dat wij hongerlijden; daarom zijn zij uit het legerkamp gegaan om zich in het veld te verstoppen. Zij zeggen: Zodra zij de stad uitgekomen zijn, zullen wij hen levend grijpen en de stad binnengaan."
    },
    {
      "verse": 13,
      "text": "Toen antwoordde een van zijn dienaren en zei: Laat men toch vijf van de overgebleven paarden nemen, die hierbinnen overgebleven zijn – zie, ze zijn als de hele menigte van de Israëlieten die hierbinnen overgebleven zijn;"
    },
    {
      "verse": 13,
      "text": "of"
    },
    {
      "verse": 13,
      "text": "zie, ze worden als de hele menigte van de Israëlieten die omgekomen zijn – en laten wij die eropuit sturen om te zien"
    },
    {
      "verse": 13,
      "text": "wat er gaande is"
    },
    {
      "verse": 13,
      "text": "."
    },
    {
      "verse": 14,
      "text": "Daarop namen zij twee strijdwagens met paarden. De koning stuurde die het leger van de Syriërs achterna en zei: Ga kijken."
    },
    {
      "verse": 15,
      "text": "Zij volgden hen tot aan de Jordaan, en zie, de hele weg lag vol met kleren en stukken uitrusting, die de Syriërs in hun haast weggeworpen hadden. De boden keerden terug en vertelden het de koning."
    },
    {
      "verse": 16,
      "text": "Toen ging het volk"
    },
    {
      "verse": 16,
      "text": "de stad"
    },
    {
      "verse": 16,
      "text": "uit en plunderde het legerkamp van de Syriërs. En een maat meelbloem werd"
    },
    {
      "verse": 16,
      "text": "verkocht"
    },
    {
      "verse": 16,
      "text": "voor een sikkel, en twee maten gerst voor een sikkel, overeenkomstig het woord van de"
    },
    {
      "verse": 16,
      "text": "HEERE"
    },
    {
      "verse": 16,
      "text": "."
    },
    {
      "verse": 17,
      "text": "De koning nu had de officier op wiens hand hij leunde, over de poort aangesteld, maar het volk vertrapte hem in de poort, zodat hij stierf, zoals de man Gods gesproken had, die dit sprak toen de koning bij hem gekomen was."
    },
    {
      "verse": 18,
      "text": "Zo is het gebeurd zoals de man Gods tot de koning gesproken had: Morgen omstreeks deze tijd zullen in de poort van Samaria twee maten gerst voor een sikkel en een maat meelbloem voor een sikkel"
    },
    {
      "verse": 18,
      "text": "verkocht"
    },
    {
      "verse": 18,
      "text": "worden."
    },
    {
      "verse": 19,
      "text": "En die officier had de man Gods geantwoord en gezegd: Zie, al maakt de"
    },
    {
      "verse": 19,
      "text": "HEERE"
    },
    {
      "verse": 19,
      "text": "sluizen in de hemel, zou dit zo"
    },
    {
      "verse": 19,
      "text": "kunnen"
    },
    {
      "verse": 19,
      "text": "gebeuren? En hij had gezegd: Zie, u zult het met uw ogen zien, maar er niet van eten."
    },
    {
      "verse": 20,
      "text": "Zo gebeurde het met hem, want het volk vertrapte hem in de poort, zodat hij stierf."
    }
  ],
  "full_text": "1 Toen zei Elisa: Hoor het woord van de\n1 HEERE\n1 . Zo zegt de\n1 HEERE\n1 : Morgen omstreeks deze tijd zal in de poort van Samaria een maat meelbloem\n1 verkocht worden\n1 voor een\n1 zilveren\n1 sikkel,\n1 en twee maten\n1 gerst voor een sikkel.\n2 Maar een officier, op wiens hand de koning leunde, antwoordde de man Gods en zei: Zie, al maakt de\n2 HEERE\n2 sluizen in de hemel – hoe zou dit\n2 kunnen\n2 gebeuren? Maar hij zei: Zie, u zult het met uw ogen zien, maar er niet van eten.\n3 Er waren vier melaatse mannen\n3 bij\n3 de ingang van de poort. Zij zeiden tegen elkaar: Waarom blijven wij hier totdat wij sterven?\n4 Als wij zeggen: Wij zullen de stad binnengaan – er is honger in de stad, dan zullen wij daar sterven; en als wij hier blijven, zullen wij\n4 ook\n4 sterven. Nu dan, kom, laten wij naar het legerkamp van de Syriërs overlopen. Als zij ons laten leven,\n4 dan\n4 zullen wij leven, en als zij ons doden, laten we\n4 dan maar\n4 sterven.\n5 En in de\n5 avond\n5 schemering stonden zij op om het legerkamp van de Syriërs in te gaan. Toen zij aan de rand van het legerkamp van de Syriërs kwamen, zie, was er niemand.\n6 De Heere had het leger van de Syriërs namelijk een\n6 geluid laten horen van strijdwagens en een geluid van paarden – het geluid van een groot leger – zodat zij tegen elkaar zeiden: Zie, de koning van Israël heeft de koningen van de Hethieten en de koningen van de Egyptenaren tegen ons ingehuurd om ons aan te vallen.\n7 Zij waren opgesprongen en in de\n7 avond\n7 schemering weggevlucht. Zij hadden hun tenten achtergelaten, hun paarden en hun ezels,\n7 en\n7 het legerkamp zoals het was, en waren gevlucht voor hun leven.\n8 Toen nu deze melaatsen aan de rand van het legerkamp kwamen, gingen zij een tent binnen, aten en dronken, namen vandaar zilver, goud en kleren mee, en gingen het verbergen. Daarna keerden zij terug, gingen een andere tent binnen, namen ook daaruit\n8 het een en ander\n8 weg en gingen het\n8 eveneens\n8 verbergen.\n9 Toen zeiden zij tegen elkaar: Wij doen\n9 hier\n9 niet goed\n9 aan\n9 . Deze dag is een dag met een goede boodschap en wij zwijgen\n9 erover\n9 . Als wij wachten tot het morgenlicht, staan wij schuldig.\n9 Nu dan, kom, laten wij\n9 dit\n9 in het huis van de koning gaan vertellen.\n10 Zij kwamen, riepen naar de poortwachter van de stad en vertelden hun: Wij zijn naar het legerkamp van de Syriërs gegaan, en zie, daar was niemand\n10 meer\n10 – geen geluid van mensen, alleen de paarden, vastgebonden; en de ezels, vastgebonden; en de tenten, zoals zij waren.\n11 En deze riep de\n11 andere\n11 poortwachters en die vertelden\n11 het\n11 binnen in het huis van de koning.\n12 En de koning stond 's nachts op en zei tegen zijn dienaren: Laat mij u toch vertellen wat de Syriërs ons gedaan hebben. Zij weten dat wij hongerlijden; daarom zijn zij uit het legerkamp gegaan om zich in het veld te verstoppen. Zij zeggen: Zodra zij de stad uitgekomen zijn, zullen wij hen levend grijpen en de stad binnengaan.\n13 Toen antwoordde een van zijn dienaren en zei: Laat men toch vijf van de overgebleven paarden nemen, die hierbinnen overgebleven zijn – zie, ze zijn als de hele menigte van de Israëlieten die hierbinnen overgebleven zijn;\n13 of\n13 zie, ze worden als de hele menigte van de Israëlieten die omgekomen zijn – en laten wij die eropuit sturen om te zien\n13 wat er gaande is\n13 .\n14 Daarop namen zij twee strijdwagens met paarden. De koning stuurde die het leger van de Syriërs achterna en zei: Ga kijken.\n15 Zij volgden hen tot aan de Jordaan, en zie, de hele weg lag vol met kleren en stukken uitrusting, die de Syriërs in hun haast weggeworpen hadden. De boden keerden terug en vertelden het de koning.\n16 Toen ging het volk\n16 de stad\n16 uit en plunderde het legerkamp van de Syriërs. En een maat meelbloem werd\n16 verkocht\n16 voor een sikkel, en twee maten gerst voor een sikkel, overeenkomstig het woord van de\n16 HEERE\n16 .\n17 De koning nu had de officier op wiens hand hij leunde, over de poort aangesteld, maar het volk vertrapte hem in de poort, zodat hij stierf, zoals de man Gods gesproken had, die dit sprak toen de koning bij hem gekomen was.\n18 Zo is het gebeurd zoals de man Gods tot de koning gesproken had: Morgen omstreeks deze tijd zullen in de poort van Samaria twee maten gerst voor een sikkel en een maat meelbloem voor een sikkel\n18 verkocht\n18 worden.\n19 En die officier had de man Gods geantwoord en gezegd: Zie, al maakt de\n19 HEERE\n19 sluizen in de hemel, zou dit zo\n19 kunnen\n19 gebeuren? En hij had gezegd: Zie, u zult het met uw ogen zien, maar er niet van eten.\n20 Zo gebeurde het met hem, want het volk vertrapte hem in de poort, zodat hij stierf.",
  "verse_count": 84,
  "translation": "HSV"
}