{
  "book": "2CH",
  "chapter": 28,
  "url": "https://www.debijbel.nl/bijbel/NBV21/2CH.28",
  "verses": [
    {
      "verse": 1,
      "text": "Achaz was twintig jaar oud toen hij koning werd. Zestien jaar regeerde hij in Jeruzalem. Hij deed niet wat goed is in de ogen van de"
    },
    {
      "verse": 1,
      "text": "HEER"
    },
    {
      "verse": 1,
      "text": ", zoals zijn voorvader David,"
    },
    {
      "verse": 2,
      "text": "maar volgde het voorbeeld van de koningen van Israël. Hij ging zelfs zo ver dat hij godenbeelden maakte voor de Baäls."
    },
    {
      "verse": 3,
      "text": "Ook ontstak hij offers in het Hinnomdal en verbrandde hij zijn zonen als offer volgens het gruwelijke gebruik van de volken die de"
    },
    {
      "verse": 3,
      "text": "HEER"
    },
    {
      "verse": 3,
      "text": "voor de Israëlieten had verdreven."
    },
    {
      "verse": 4,
      "text": "Hij bracht offers en brandde wierook op de offerplaatsen, op de heuvels en onder elke bladerrijke boom."
    },
    {
      "verse": 5,
      "text": "De"
    },
    {
      "verse": 5,
      "text": "HEER"
    },
    {
      "verse": 5,
      "text": ", zijn God, leverde hem uit aan de koning van Aram. De Arameeërs versloegen hem en voerden een grote groep gevangenen naar Damascus weg. Vervolgens werd hij overgeleverd aan de koning van Israël, die een grote overwinning op hem behaalde."
    },
    {
      "verse": 6,
      "text": "Pekach, de zoon van Remaljahu, doodde in Juda honderdtwintigduizend man op één dag, allen geoefende krijgslieden, omdat zij zich van de"
    },
    {
      "verse": 6,
      "text": "HEER"
    },
    {
      "verse": 6,
      "text": ", de God van hun voorouders, hadden afgekeerd."
    },
    {
      "verse": 7,
      "text": "Zichri, de held van Efraïm, doodde Maäseja, de zoon van de koning, Azrikam, de hofmeester, en Elkana, de tweede man aan het hof."
    },
    {
      "verse": 8,
      "text": "De Israëlieten voerden tweehonderdduizend vrouwen, zonen en dochters van hun broeders als gevangenen weg en ontroofden hun een grote buit, die ze meenamen naar Samaria."
    },
    {
      "verse": 9,
      "text": "In Samaria woonde een profeet van de"
    },
    {
      "verse": 9,
      "text": "HEER"
    },
    {
      "verse": 9,
      "text": ", Oded genaamd. Toen het leger naar Samaria terugkeerde, ging hij het tegemoet en zei: ‘De"
    },
    {
      "verse": 9,
      "text": "HEER"
    },
    {
      "verse": 9,
      "text": ", de God van uw voorouders, heeft de Judeeërs aan u uitgeleverd omdat Hij woedend op hen was. Met een razernij die tot in de hemel reikte hebt u velen van hen gedood."
    },
    {
      "verse": 10,
      "text": "En nu bent u van plan de mensen uit Juda en Jeruzalem als slaven en slavinnen te onderwerpen. Bent u niet evengoed met schuld beladen tegenover de"
    },
    {
      "verse": 10,
      "text": "HEER"
    },
    {
      "verse": 10,
      "text": ", uw God?"
    },
    {
      "verse": 11,
      "text": "Welnu, luister goed, stuur de gevangenen die u van uw broeders hebt weggevoerd terug, want u hebt de toorn van de"
    },
    {
      "verse": 11,
      "text": "HEER"
    },
    {
      "verse": 11,
      "text": "over u afgeroepen.’"
    },
    {
      "verse": 12,
      "text": "Enkele familiehoofden uit de stam Efraïm, Azarja, de zoon van Jochanan, Berechja, de zoon van Mesillemot, Jechizkia, de zoon van Sallum, en Amasa, de zoon van Chadlai, traden de binnentrekkende legermacht tegemoet"
    },
    {
      "verse": 13,
      "text": "en zeiden: ‘Breng de gevangenen niet hierheen. Wanneer u doet wat u van plan bent, belaadt u ons met schuld tegenover de"
    },
    {
      "verse": 13,
      "text": "HEER"
    },
    {
      "verse": 13,
      "text": ". U zou onze zonden en schulden nog vermeerderen, terwijl onze schuld nu al zo groot is dat wij de toorn van de"
    },
    {
      "verse": 13,
      "text": "HEER"
    },
    {
      "verse": 13,
      "text": "hebben opgewekt.’"
    },
    {
      "verse": 14,
      "text": "Hierop droegen de soldaten de gevangenen en de buit aan de leiders en het aanwezige volk over."
    },
    {
      "verse": 15,
      "text": "Speciaal daartoe aangewezen mannen namen de gevangenen onder hun hoede. Met wat in de buit voorhanden was kleedden ze degenen die naakt waren. Ze kleedden en schoeiden ze, gaven hun te eten en te drinken, verzorgden hun wonden en zetten degenen die moeizaam voortstrompelden op ezels. Zo begeleidden ze hen tot aan de palmstad Jericho, aan de grens met het gebied van hun broeders, waarna ze terugkeerden naar Samaria."
    },
    {
      "verse": 16,
      "text": "Het was in diezelfde tijd dat koning Achaz de hulp inriep van de koning van Assyrië."
    },
    {
      "verse": 17,
      "text": "Ook de Edomieten waren namelijk Juda binnengevallen en hadden gevangenen weggevoerd."
    },
    {
      "verse": 18,
      "text": "En de Filistijnen hadden aanvallen gedaan op verschillende steden in het heuvelland en het Judese gedeelte van de Negev. Ze hadden Bet-Semes, Ajjalon en Gederot, en Socho, Timna en Gimzo en de omliggende dorpen veroverd en zich daar gevestigd."
    },
    {
      "verse": 19,
      "text": "De"
    },
    {
      "verse": 19,
      "text": "HEER"
    },
    {
      "verse": 19,
      "text": "had Juda vernederd omdat Achaz als koning van de Israëlieten de zeden in Juda had laten verwilderen en zijn plicht tegenover de"
    },
    {
      "verse": 19,
      "text": "HEER"
    },
    {
      "verse": 19,
      "text": "had verzaakt."
    },
    {
      "verse": 20,
      "text": "Maar in plaats van Achaz te helpen, viel koning Tiglatpileser van Assyrië hem aan en dreef hij hem in het nauw."
    },
    {
      "verse": 21,
      "text": "Achaz had weliswaar de tempel van de"
    },
    {
      "verse": 21,
      "text": "HEER"
    },
    {
      "verse": 21,
      "text": ", het koninklijk paleis en de huizen van de hoogwaardigheidsbekleders leeggehaald en de schatten aan de koning van Assyrië gegeven, maar toch kwam die hem niet te hulp."
    },
    {
      "verse": 22,
      "text": "Toen hij zo in het nauw was gedreven, beging hij, koning Achaz, nog meer overtredingen tegenover de"
    },
    {
      "verse": 22,
      "text": "HEER"
    },
    {
      "verse": 22,
      "text": "."
    },
    {
      "verse": 23,
      "text": "Hij bracht offers aan de goden van Damascus, die hem verslagen hadden, want hij dacht bij zichzelf: De goden van de koningen van Aram helpen hun volk wél. Als ik hun offers breng, helpen ze mij vast ook. Maar zij brachten hem en heel Israël juist ten val."
    },
    {
      "verse": 24,
      "text": "Achaz haalde alle voorwerpen uit de tempel van God en sloeg ze aan stukken. Hij liet de tempel van de"
    },
    {
      "verse": 24,
      "text": "HEER"
    },
    {
      "verse": 24,
      "text": "sluiten en plaatste altaren op alle straathoeken van Jeruzalem."
    },
    {
      "verse": 25,
      "text": "En hij tergde de"
    },
    {
      "verse": 25,
      "text": "HEER"
    },
    {
      "verse": 25,
      "text": ", de God van zijn voorouders, nog verder door in alle steden van Juda offerplaatsen voor andere goden in te richten."
    },
    {
      "verse": 26,
      "text": "Alle verdere bijzonderheden over Achaz zijn van begin tot eind opgetekend in het boek over de koningen van Juda en Israël."
    },
    {
      "verse": 27,
      "text": "Toen hij stierf, werd hij wel in Jeruzalem begraven, maar niet bijgezet in de graven van de koningen van Israël. Zijn zoon Jechizkia volgde hem op."
    }
  ],
  "full_text": "1 Achaz was twintig jaar oud toen hij koning werd. Zestien jaar regeerde hij in Jeruzalem. Hij deed niet wat goed is in de ogen van de\n1 HEER\n1 , zoals zijn voorvader David,\n2 maar volgde het voorbeeld van de koningen van Israël. Hij ging zelfs zo ver dat hij godenbeelden maakte voor de Baäls.\n3 Ook ontstak hij offers in het Hinnomdal en verbrandde hij zijn zonen als offer volgens het gruwelijke gebruik van de volken die de\n3 HEER\n3 voor de Israëlieten had verdreven.\n4 Hij bracht offers en brandde wierook op de offerplaatsen, op de heuvels en onder elke bladerrijke boom.\n5 De\n5 HEER\n5 , zijn God, leverde hem uit aan de koning van Aram. De Arameeërs versloegen hem en voerden een grote groep gevangenen naar Damascus weg. Vervolgens werd hij overgeleverd aan de koning van Israël, die een grote overwinning op hem behaalde.\n6 Pekach, de zoon van Remaljahu, doodde in Juda honderdtwintigduizend man op één dag, allen geoefende krijgslieden, omdat zij zich van de\n6 HEER\n6 , de God van hun voorouders, hadden afgekeerd.\n7 Zichri, de held van Efraïm, doodde Maäseja, de zoon van de koning, Azrikam, de hofmeester, en Elkana, de tweede man aan het hof.\n8 De Israëlieten voerden tweehonderdduizend vrouwen, zonen en dochters van hun broeders als gevangenen weg en ontroofden hun een grote buit, die ze meenamen naar Samaria.\n9 In Samaria woonde een profeet van de\n9 HEER\n9 , Oded genaamd. Toen het leger naar Samaria terugkeerde, ging hij het tegemoet en zei: ‘De\n9 HEER\n9 , de God van uw voorouders, heeft de Judeeërs aan u uitgeleverd omdat Hij woedend op hen was. Met een razernij die tot in de hemel reikte hebt u velen van hen gedood.\n10 En nu bent u van plan de mensen uit Juda en Jeruzalem als slaven en slavinnen te onderwerpen. Bent u niet evengoed met schuld beladen tegenover de\n10 HEER\n10 , uw God?\n11 Welnu, luister goed, stuur de gevangenen die u van uw broeders hebt weggevoerd terug, want u hebt de toorn van de\n11 HEER\n11 over u afgeroepen.’\n12 Enkele familiehoofden uit de stam Efraïm, Azarja, de zoon van Jochanan, Berechja, de zoon van Mesillemot, Jechizkia, de zoon van Sallum, en Amasa, de zoon van Chadlai, traden de binnentrekkende legermacht tegemoet\n13 en zeiden: ‘Breng de gevangenen niet hierheen. Wanneer u doet wat u van plan bent, belaadt u ons met schuld tegenover de\n13 HEER\n13 . U zou onze zonden en schulden nog vermeerderen, terwijl onze schuld nu al zo groot is dat wij de toorn van de\n13 HEER\n13 hebben opgewekt.’\n14 Hierop droegen de soldaten de gevangenen en de buit aan de leiders en het aanwezige volk over.\n15 Speciaal daartoe aangewezen mannen namen de gevangenen onder hun hoede. Met wat in de buit voorhanden was kleedden ze degenen die naakt waren. Ze kleedden en schoeiden ze, gaven hun te eten en te drinken, verzorgden hun wonden en zetten degenen die moeizaam voortstrompelden op ezels. Zo begeleidden ze hen tot aan de palmstad Jericho, aan de grens met het gebied van hun broeders, waarna ze terugkeerden naar Samaria.\n16 Het was in diezelfde tijd dat koning Achaz de hulp inriep van de koning van Assyrië.\n17 Ook de Edomieten waren namelijk Juda binnengevallen en hadden gevangenen weggevoerd.\n18 En de Filistijnen hadden aanvallen gedaan op verschillende steden in het heuvelland en het Judese gedeelte van de Negev. Ze hadden Bet-Semes, Ajjalon en Gederot, en Socho, Timna en Gimzo en de omliggende dorpen veroverd en zich daar gevestigd.\n19 De\n19 HEER\n19 had Juda vernederd omdat Achaz als koning van de Israëlieten de zeden in Juda had laten verwilderen en zijn plicht tegenover de\n19 HEER\n19 had verzaakt.\n20 Maar in plaats van Achaz te helpen, viel koning Tiglatpileser van Assyrië hem aan en dreef hij hem in het nauw.\n21 Achaz had weliswaar de tempel van de\n21 HEER\n21 , het koninklijk paleis en de huizen van de hoogwaardigheidsbekleders leeggehaald en de schatten aan de koning van Assyrië gegeven, maar toch kwam die hem niet te hulp.\n22 Toen hij zo in het nauw was gedreven, beging hij, koning Achaz, nog meer overtredingen tegenover de\n22 HEER\n22 .\n23 Hij bracht offers aan de goden van Damascus, die hem verslagen hadden, want hij dacht bij zichzelf: De goden van de koningen van Aram helpen hun volk wél. Als ik hun offers breng, helpen ze mij vast ook. Maar zij brachten hem en heel Israël juist ten val.\n24 Achaz haalde alle voorwerpen uit de tempel van God en sloeg ze aan stukken. Hij liet de tempel van de\n24 HEER\n24 sluiten en plaatste altaren op alle straathoeken van Jeruzalem.\n25 En hij tergde de\n25 HEER\n25 , de God van zijn voorouders, nog verder door in alle steden van Juda offerplaatsen voor andere goden in te richten.\n26 Alle verdere bijzonderheden over Achaz zijn van begin tot eind opgetekend in het boek over de koningen van Juda en Israël.\n27 Toen hij stierf, werd hij wel in Jeruzalem begraven, maar niet bijgezet in de graven van de koningen van Israël. Zijn zoon Jechizkia volgde hem op.",
  "verse_count": 59,
  "translation": "HSV"
}